<annotation>
	<folder>CA3</folder>
	<filename>AI_MS_D8_72417_CA3_IBA1_20x_4.jpg</filename>
	<path>/Users/kevin/Desktop/Quantitation/D8/CA3/AI_MS_D8_72417_CA3_IBA1_20x_4.tif</path>
	<source>
		<database>Unknown</database>
	</source>
	<size>
		<width>1600</width>
		<height>1200</height>
		<depth>3</depth>
	</size>
	<segmented>0</segmented>
	<object>
		<name>Microglia</name>
		<pose>Unspecified</pose>
		<truncated>0</truncated>
		<difficult>0</difficult>
		<bndbox>
			<xmin>274</xmin>
			<ymin>729</ymin>
			<xmax>309</xmax>
			<ymax>779</ymax>
		</bndbox>
	</object>
	<object>
		<name>Microglia</name>
		<pose>Unspecified</pose>
		<truncated>0</truncated>
		<difficult>0</difficult>
		<bndbox>
			<xmin>283</xmin>
			<ymin>818</ymin>
			<xmax>332</xmax>
			<ymax>853</ymax>
		</bndbox>
	</object>
	<object>
		<name>Microglia</name>
		<pose>Unspecified</pose>
		<truncated>0</truncated>
		<difficult>0</difficult>
		<bndbox>
			<xmin>172</xmin>
			<ymin>839</ymin>
			<xmax>221</xmax>
			<ymax>874</ymax>
		</bndbox>
	</object>
	<object>
		<name>Microglia</name>
		<pose>Unspecified</pose>
		<truncated>0</truncated>
		<difficult>0</difficult>
		<bndbox>
			<xmin>50</xmin>
			<ymin>306</ymin>
			<xmax>98</xmax>
			<ymax>348</ymax>
		</bndbox>
	</object>
	<object>
		<name>Microglia</name>
		<pose>Unspecified</pose>
		<truncated>0</truncated>
		<difficult>0</difficult>
		<bndbox>
			<xmin>22</xmin>
			<ymin>156</ymin>
			<xmax>69</xmax>
			<ymax>193</ymax>
		</bndbox>
	</object>
	<object>
		<name>Microglia</name>
		<pose>Unspecified</pose>
		<truncated>0</truncated>
		<difficult>0</difficult>
		<bndbox>
			<xmin>1045</xmin>
			<ymin>306</ymin>
			<xmax>1088</xmax>
			<ymax>361</ymax>
		</bndbox>
	</object>
	<object>
		<name>Microglia</name>
		<pose>Unspecified</pose>
		<truncated>0</truncated>
		<difficult>0</difficult>
		<bndbox>
			<xmin>1193</xmin>
			<ymin>177</ymin>
			<xmax>1264</xmax>
			<ymax>213</ymax>
		</bndbox>
	</object>
	<object>
		<name>Microglia</name>
		<pose>Unspecified</pose>
		<truncated>0</truncated>
		<difficult>0</difficult>
		<bndbox>
			<xmin>1496</xmin>
			<ymin>495</ymin>
			<xmax>1548</xmax>
			<ymax>543</ymax>
		</bndbox>
	</object>
	<object>
		<name>Microglia</name>
		<pose>Unspecified</pose>
		<truncated>0</truncated>
		<difficult>0</difficult>
		<bndbox>
			<xmin>1450</xmin>
			<ymin>939</ymin>
			<xmax>1501</xmax>
			<ymax>987</ymax>
		</bndbox>
	</object>
	<object>
		<name>Microglia</name>
		<pose>Unspecified</pose>
		<truncated>0</truncated>
		<difficult>0</difficult>
		<bndbox>
			<xmin>1188</xmin>
			<ymin>1039</ymin>
			<xmax>1250</xmax>
			<ymax>1097</ymax>
		</bndbox>
	</object>
	<object>
		<name>Microglia</name>
		<pose>Unspecified</pose>
		<truncated>0</truncated>
		<difficult>0</difficult>
		<bndbox>
			<xmin>1135</xmin>
			<ymin>960</ymin>
			<xmax>1169</xmax>
			<ymax>1006</ymax>
		</bndbox>
	</object>
	<object>
		<name>Microglia</name>
		<pose>Unspecified</pose>
		<truncated>0</truncated>
		<difficult>0</difficult>
		<bndbox>
			<xmin>1138</xmin>
			<ymin>732</ymin>
			<xmax>1172</xmax>
			<ymax>772</ymax>
		</bndbox>
	</object>
	<object>
		<name>Microglia</name>
		<pose>Unspecified</pose>
		<truncated>0</truncated>
		<difficult>0</difficult>
		<bndbox>
			<xmin>1200</xmin>
			<ymin>551</ymin>
			<xmax>1280</xmax>
			<ymax>584</ymax>
		</bndbox>
	</object>
	<object>
		<name>Microglia</name>
		<pose>Unspecified</pose>
		<truncated>0</truncated>
		<difficult>0</difficult>
		<bndbox>
			<xmin>1406</xmin>
			<ymin>266</ymin>
			<xmax>1448</xmax>
			<ymax>297</ymax>
		</bndbox>
	</object>
	<object>
		<name>Microglia</name>
		<pose>Unspecified</pose>
		<truncated>0</truncated>
		<difficult>0</difficult>
		<bndbox>
			<xmin>1038</xmin>
			<ymin>497</ymin>
			<xmax>1079</xmax>
			<ymax>526</ymax>
		</bndbox>
	</object>
	<object>
		<name>Microglia</name>
		<pose>Unspecified</pose>
		<truncated>0</truncated>
		<difficult>0</difficult>
		<bndbox>
			<xmin>919</xmin>
			<ymin>661</ymin>
			<xmax>959</xmax>
			<ymax>708</ymax>
		</bndbox>
	</object>
	<object>
		<name>Microglia</name>
		<pose>Unspecified</pose>
		<truncated>0</truncated>
		<difficult>0</difficult>
		<bndbox>
			<xmin>796</xmin>
			<ymin>848</ymin>
			<xmax>845</xmax>
			<ymax>919</ymax>
		</bndbox>
	</object>
	<object>
		<name>Microglia</name>
		<pose>Unspecified</pose>
		<truncated>0</truncated>
		<difficult>0</difficult>
		<bndbox>
			<xmin>490</xmin>
			<ymin>1001</ymin>
			<xmax>527</xmax>
			<ymax>1035</ymax>
		</bndbox>
	</object>
	<object>
		<name>Microglia</name>
		<pose>Unspecified</pose>
		<truncated>0</truncated>
		<difficult>0</difficult>
		<bndbox>
			<xmin>193</xmin>
			<ymin>411</ymin>
			<xmax>230</xmax>
			<ymax>464</ymax>
		</bndbox>
	</object>
	<object>
		<name>Microglia</name>
		<pose>Unspecified</pose>
		<truncated>0</truncated>
		<difficult>0</difficult>
		<bndbox>
			<xmin>324</xmin>
			<ymin>126</ymin>
			<xmax>356</xmax>
			<ymax>171</ymax>
		</bndbox>
	</object>
	<object>
		<name>Microglia</name>
		<pose>Unspecified</pose>
		<truncated>0</truncated>
		<difficult>0</difficult>
		<bndbox>
			<xmin>796</xmin>
			<ymin>90</ymin>
			<xmax>851</xmax>
			<ymax>153</ymax>
		</bndbox>
	</object>
	<object>
		<name>Microglia</name>
		<pose>Unspecified</pose>
		<truncated>0</truncated>
		<difficult>0</difficult>
		<bndbox>
			<xmin>529</xmin>
			<ymin>400</ymin>
			<xmax>572</xmax>
			<ymax>443</ymax>
		</bndbox>
	</object>
	<object>
		<name>Microglia</name>
		<pose>Unspecified</pose>
		<truncated>0</truncated>
		<difficult>0</difficult>
		<bndbox>
			<xmin>440</xmin>
			<ymin>1150</ymin>
			<xmax>482</xmax>
			<ymax>1193</ymax>
		</bndbox>
	</object>
	<object>
		<name>Microglia</name>
		<pose>Unspecified</pose>
		<truncated>0</truncated>
		<difficult>0</difficult>
		<bndbox>
			<xmin>803</xmin>
			<ymin>627</ymin>
			<xmax>838</xmax>
			<ymax>689</ymax>
		</bndbox>
	</object>
	<object>
		<name>Microglia</name>
		<pose>Unspecified</pose>
		<truncated>0</truncated>
		<difficult>0</difficult>
		<bndbox>
			<xmin>1553</xmin>
			<ymin>11</ymin>
			<xmax>1596</xmax>
			<ymax>53</ymax>
		</bndbox>
	</object>
	<object>
		<name>Microglia</name>
		<pose>Unspecified</pose>
		<truncated>0</truncated>
		<difficult>0</difficult>
		<bndbox>
			<xmin>211</xmin>
			<ymin>45</ymin>
			<xmax>261</xmax>
			<ymax>85</ymax>
		</bndbox>
	</object>
	<object>
		<name>Microglia</name>
		<pose>Unspecified</pose>
		<truncated>0</truncated>
		<difficult>0</difficult>
		<bndbox>
			<xmin>859</xmin>
			<ymin>1139</ymin>
			<xmax>908</xmax>
			<ymax>1180</ymax>
		</bndbox>
	</object>
</annotation>
